vpt_plugin_watershed/__init__.py
vpt_plugin_watershed/segment.py
vpt_plugin_watershed/stardist/__init__.py
vpt_plugin_watershed/stardist/seeds.py
vpt_plugin_watershed/stardist/utils.py
vpt_plugin_watershed/watershed/__init__.py
vpt_plugin_watershed/watershed/entity.py
vpt_plugin_watershed/watershed/seeds.py
vpt_plugin_watershed/watershed/segmentation.py
vpt_plugin_watershed/watershed/validate.py
vpt_plugin_watershed-1.0.2.dist-info/LICENSE.md
vpt_plugin_watershed-1.0.2.dist-info/METADATA
vpt_plugin_watershed-1.0.2.dist-info/WHEEL
vpt_plugin_watershed-1.0.2.dist-info/RECORD
